dlab/__init__.py
dlab/cache.py
dlab/core.py
dlab/get_songs.py
dlab/kilo.py
dlab/neurobank.py
dlab/plotting.py
dlab/pprox.py
dlab/signal.py
dlab/spikes.py
dlab/util.py
melizalab_tools-2025.8.27.dist-info/METADATA
melizalab_tools-2025.8.27.dist-info/WHEEL
melizalab_tools-2025.8.27.dist-info/entry_points.txt
melizalab_tools-2025.8.27.dist-info/RECORD
