Metadata-Version: 2.4
Name: melizalab-tools
Version: 2025.8.27
Summary: Meliza lab scripts and modules for auditory neurophysiology
Project-URL: Homepage, https://github.com/melizalab/melizalab-tools
Author-email: C Daniel Meliza <dan@meliza.org>
Maintainer-email: C Daniel Meliza <dan@meliza.org>
License: BSD 3-Clause License
Classifier: Development Status :: 3 - Alpha
Classifier: Intended Audience :: Science/Research
Classifier: License :: OSI Approved :: BSD License
Classifier: Programming Language :: Python
Classifier: Programming Language :: Python :: 3.10
Classifier: Programming Language :: Python :: 3.11
Classifier: Programming Language :: Python :: 3.12
Requires-Python: >=3.10
Requires-Dist: appdirs>=1.4.4
Requires-Dist: arf>=2.7.1
Requires-Dist: ewave>=1.0.10
Requires-Dist: libtfr>=2.1.9
Requires-Dist: neurobank>=0.11.1
Requires-Dist: pandas>=2.3.1
Requires-Dist: pyyaml>=6.0.2
Requires-Dist: quickspikes>=2.0.6
Requires-Dist: scipy>=1.15.3
Requires-Dist: toelis>=2.1.4
Provides-Extra: audio
Requires-Dist: samplerate>=0.2.1; extra == 'audio'
